{"nodes": [{"id": "streamlit_app_pages_3_stock_detail_py", "label": "3_Stock_Detail.py", "file_type": "code", "source_file": "streamlit_app\\pages\\3_Stock_Detail.py", "source_location": "L1"}, {"id": "3_stock_detail_render_sidebar", "label": "_render_sidebar()", "file_type": "code", "source_file": "streamlit_app\\pages\\3_Stock_Detail.py", "source_location": "L33"}, {"id": "3_stock_detail_fetch_stock_info", "label": "fetch_stock_info()", "file_type": "code", "source_file": "streamlit_app\\pages\\3_Stock_Detail.py", "source_location": "L49"}, {"id": "3_stock_detail_fetch_ohlcv", "label": "fetch_ohlcv()", "file_type": "code", "source_file": "streamlit_app\\pages\\3_Stock_Detail.py", "source_location": "L57"}, {"id": "3_stock_detail_fetch_stock_quote", "label": "fetch_stock_quote()", "file_type": "code", "source_file": "streamlit_app\\pages\\3_Stock_Detail.py", "source_location": "L65"}, {"id": "3_stock_detail_fetch_indicators", "label": "fetch_indicators()", "file_type": "code", "source_file": "streamlit_app\\pages\\3_Stock_Detail.py", "source_location": "L73"}, {"id": "3_stock_detail_fetch_sentiment", "label": "fetch_sentiment()", "file_type": "code", "source_file": "streamlit_app\\pages\\3_Stock_Detail.py", "source_location": "L92"}, {"id": "3_stock_detail_fetch_latest_signal", "label": "fetch_latest_signal()", "file_type": "code", "source_file": "streamlit_app\\pages\\3_Stock_Detail.py", "source_location": "L111"}, {"id": "3_stock_detail_is_in_watchlist", "label": "is_in_watchlist()", "file_type": "code", "source_file": "streamlit_app\\pages\\3_Stock_Detail.py", "source_location": "L129"}, {"id": "3_stock_detail_toggle_watchlist", "label": "toggle_watchlist()", "file_type": "code", "source_file": "streamlit_app\\pages\\3_Stock_Detail.py", "source_location": "L146"}], "edges": [{"source": "streamlit_app_pages_3_stock_detail_py", "target": "sys", "relation": "imports", "confidence": "EXTRACTED", "source_file": "streamlit_app\\pages\\3_Stock_Detail.py", "source_location": "L3", "weight": 1.0}, {"source": "streamlit_app_pages_3_stock_detail_py", "target": "pathlib", "relation": "imports_from", "confidence": "EXTRACTED", "source_file": "streamlit_app\\pages\\3_Stock_Detail.py", "source_location": "L4", "weight": 1.0}, {"source": "streamlit_app_pages_3_stock_detail_py", "target": "plotly_graph_objects", "relation": "imports", "confidence": "EXTRACTED", "source_file": "streamlit_app\\pages\\3_Stock_Detail.py", "source_location": "L9", "weight": 1.0}, {"source": "streamlit_app_pages_3_stock_detail_py", "target": "streamlit", "relation": "imports", "confidence": "EXTRACTED", "source_file": "streamlit_app\\pages\\3_Stock_Detail.py", "source_location": "L10", "weight": 1.0}, {"source": "streamlit_app_pages_3_stock_detail_py", "target": "api_client", "relation": "imports_from", "confidence": "EXTRACTED", "source_file": "streamlit_app\\pages\\3_Stock_Detail.py", "source_location": "L12", "weight": 1.0}, {"source": "streamlit_app_pages_3_stock_detail_py", "target": "auth", "relation": "imports_from", "confidence": "EXTRACTED", "source_file": "streamlit_app\\pages\\3_Stock_Detail.py", "source_location": "L13", "weight": 1.0}, {"source": "streamlit_app_pages_3_stock_detail_py", "target": "design", "relation": "imports_from", "confidence": "EXTRACTED", "source_file": "streamlit_app\\pages\\3_Stock_Detail.py", "source_location": "L14", "weight": 1.0}, {"source": "streamlit_app_pages_3_stock_detail_py", "target": "supabase_client", "relation": "imports_from", "confidence": "EXTRACTED", "source_file": "streamlit_app\\pages\\3_Stock_Detail.py", "source_location": "L25", "weight": 1.0}, {"source": "streamlit_app_pages_3_stock_detail_py", "target": "utils", "relation": "imports_from", "confidence": "EXTRACTED", "source_file": "streamlit_app\\pages\\3_Stock_Detail.py", "source_location": "L26", "weight": 1.0}, {"source": "streamlit_app_pages_3_stock_detail_py", "target": "3_stock_detail_render_sidebar", "relation": "contains", "confidence": "EXTRACTED", "source_file": "streamlit_app\\pages\\3_Stock_Detail.py", "source_location": "L33", "weight": 1.0}, {"source": "streamlit_app_pages_3_stock_detail_py", "target": "3_stock_detail_fetch_stock_info", "relation": "contains", "confidence": "EXTRACTED", "source_file": "streamlit_app\\pages\\3_Stock_Detail.py", "source_location": "L49", "weight": 1.0}, {"source": "streamlit_app_pages_3_stock_detail_py", "target": "3_stock_detail_fetch_ohlcv", "relation": "contains", "confidence": "EXTRACTED", "source_file": "streamlit_app\\pages\\3_Stock_Detail.py", "source_location": "L57", "weight": 1.0}, {"source": "streamlit_app_pages_3_stock_detail_py", "target": "3_stock_detail_fetch_stock_quote", "relation": "contains", "confidence": "EXTRACTED", "source_file": "streamlit_app\\pages\\3_Stock_Detail.py", "source_location": "L65", "weight": 1.0}, {"source": "streamlit_app_pages_3_stock_detail_py", "target": "3_stock_detail_fetch_indicators", "relation": "contains", "confidence": "EXTRACTED", "source_file": "streamlit_app\\pages\\3_Stock_Detail.py", "source_location": "L73", "weight": 1.0}, {"source": "streamlit_app_pages_3_stock_detail_py", "target": "3_stock_detail_fetch_sentiment", "relation": "contains", "confidence": "EXTRACTED", "source_file": "streamlit_app\\pages\\3_Stock_Detail.py", "source_location": "L92", "weight": 1.0}, {"source": "streamlit_app_pages_3_stock_detail_py", "target": "3_stock_detail_fetch_latest_signal", "relation": "contains", "confidence": "EXTRACTED", "source_file": "streamlit_app\\pages\\3_Stock_Detail.py", "source_location": "L111", "weight": 1.0}, {"source": "streamlit_app_pages_3_stock_detail_py", "target": "3_stock_detail_is_in_watchlist", "relation": "contains", "confidence": "EXTRACTED", "source_file": "streamlit_app\\pages\\3_Stock_Detail.py", "source_location": "L129", "weight": 1.0}, {"source": "streamlit_app_pages_3_stock_detail_py", "target": "3_stock_detail_toggle_watchlist", "relation": "contains", "confidence": "EXTRACTED", "source_file": "streamlit_app\\pages\\3_Stock_Detail.py", "source_location": "L146", "weight": 1.0}], "raw_calls": [{"caller_nid": "3_stock_detail_render_sidebar", "callee": "get_profile", "source_file": "streamlit_app\\pages\\3_Stock_Detail.py", "source_location": "L34"}, {"caller_nid": "3_stock_detail_render_sidebar", "callee": "render_sidebar_shell", "source_file": "streamlit_app\\pages\\3_Stock_Detail.py", "source_location": "L35"}, {"caller_nid": "3_stock_detail_render_sidebar", "callee": "get", "source_file": "streamlit_app\\pages\\3_Stock_Detail.py", "source_location": "L38"}, {"caller_nid": "3_stock_detail_render_sidebar", "callee": "markdown", "source_file": "streamlit_app\\pages\\3_Stock_Detail.py", "source_location": "L42"}, {"caller_nid": "3_stock_detail_render_sidebar", "callee": "button", "source_file": "streamlit_app\\pages\\3_Stock_Detail.py", "source_location": "L43"}, {"caller_nid": "3_stock_detail_render_sidebar", "callee": "logout", "source_file": "streamlit_app\\pages\\3_Stock_Detail.py", "source_location": "L44"}, {"caller_nid": "3_stock_detail_render_sidebar", "callee": "switch_page", "source_file": "streamlit_app\\pages\\3_Stock_Detail.py", "source_location": "L45"}, {"caller_nid": "3_stock_detail_fetch_stock_info", "callee": "request_json", "source_file": "streamlit_app\\pages\\3_Stock_Detail.py", "source_location": "L51"}, {"caller_nid": "3_stock_detail_fetch_ohlcv", "callee": "request_json", "source_file": "streamlit_app\\pages\\3_Stock_Detail.py", "source_location": "L59"}, {"caller_nid": "3_stock_detail_fetch_stock_quote", "callee": "request_json", "source_file": "streamlit_app\\pages\\3_Stock_Detail.py", "source_location": "L67"}, {"caller_nid": "3_stock_detail_fetch_indicators", "callee": "execute", "source_file": "streamlit_app\\pages\\3_Stock_Detail.py", "source_location": "L76"}, {"caller_nid": "3_stock_detail_fetch_indicators", "callee": "limit", "source_file": "streamlit_app\\pages\\3_Stock_Detail.py", "source_location": "L76"}, {"caller_nid": "3_stock_detail_fetch_indicators", "callee": "order", "source_file": "streamlit_app\\pages\\3_Stock_Detail.py", "source_location": "L76"}, {"caller_nid": "3_stock_detail_fetch_indicators", "callee": "eq", "source_file": "streamlit_app\\pages\\3_Stock_Detail.py", "source_location": "L76"}, {"caller_nid": "3_stock_detail_fetch_indicators", "callee": "select", "source_file": "streamlit_app\\pages\\3_Stock_Detail.py", "source_location": "L76"}, {"caller_nid": "3_stock_detail_fetch_indicators", "callee": "table", "source_file": "streamlit_app\\pages\\3_Stock_Detail.py", "source_location": "L76"}, {"caller_nid": "3_stock_detail_fetch_indicators", "callee": "get_anon_client", "source_file": "streamlit_app\\pages\\3_Stock_Detail.py", "source_location": "L76"}, {"caller_nid": "3_stock_detail_fetch_indicators", "callee": "sorted", "source_file": "streamlit_app\\pages\\3_Stock_Detail.py", "source_location": "L86"}, {"caller_nid": "3_stock_detail_fetch_sentiment", "callee": "execute", "source_file": "streamlit_app\\pages\\3_Stock_Detail.py", "source_location": "L95"}, {"caller_nid": "3_stock_detail_fetch_sentiment", "callee": "limit", "source_file": "streamlit_app\\pages\\3_Stock_Detail.py", "source_location": "L95"}, {"caller_nid": "3_stock_detail_fetch_sentiment", "callee": "order", "source_file": "streamlit_app\\pages\\3_Stock_Detail.py", "source_location": "L95"}, {"caller_nid": "3_stock_detail_fetch_sentiment", "callee": "eq", "source_file": "streamlit_app\\pages\\3_Stock_Detail.py", "source_location": "L95"}, {"caller_nid": "3_stock_detail_fetch_sentiment", "callee": "select", "source_file": "streamlit_app\\pages\\3_Stock_Detail.py", "source_location": "L95"}, {"caller_nid": "3_stock_detail_fetch_sentiment", "callee": "table", "source_file": "streamlit_app\\pages\\3_Stock_Detail.py", "source_location": "L95"}, {"caller_nid": "3_stock_detail_fetch_sentiment", "callee": "get_anon_client", "source_file": "streamlit_app\\pages\\3_Stock_Detail.py", "source_location": "L95"}, {"caller_nid": "3_stock_detail_fetch_sentiment", "callee": "sorted", "source_file": "streamlit_app\\pages\\3_Stock_Detail.py", "source_location": "L105"}, {"caller_nid": "3_stock_detail_fetch_latest_signal", "callee": "execute", "source_file": "streamlit_app\\pages\\3_Stock_Detail.py", "source_location": "L114"}, {"caller_nid": "3_stock_detail_fetch_latest_signal", "callee": "limit", "source_file": "streamlit_app\\pages\\3_Stock_Detail.py", "source_location": "L114"}, {"caller_nid": "3_stock_detail_fetch_latest_signal", "callee": "order", "source_file": "streamlit_app\\pages\\3_Stock_Detail.py", "source_location": "L114"}, {"caller_nid": "3_stock_detail_fetch_latest_signal", "callee": "eq", "source_file": "streamlit_app\\pages\\3_Stock_Detail.py", "source_location": "L114"}, {"caller_nid": "3_stock_detail_fetch_latest_signal", "callee": "select", "source_file": "streamlit_app\\pages\\3_Stock_Detail.py", "source_location": "L114"}, {"caller_nid": "3_stock_detail_fetch_latest_signal", "callee": "table", "source_file": "streamlit_app\\pages\\3_Stock_Detail.py", "source_location": "L114"}, {"caller_nid": "3_stock_detail_fetch_latest_signal", "callee": "get_anon_client", "source_file": "streamlit_app\\pages\\3_Stock_Detail.py", "source_location": "L114"}, {"caller_nid": "3_stock_detail_is_in_watchlist", "callee": "execute", "source_file": "streamlit_app\\pages\\3_Stock_Detail.py", "source_location": "L132"}, {"caller_nid": "3_stock_detail_is_in_watchlist", "callee": "eq", "source_file": "streamlit_app\\pages\\3_Stock_Detail.py", "source_location": "L132"}, {"caller_nid": "3_stock_detail_is_in_watchlist", "callee": "eq", "source_file": "streamlit_app\\pages\\3_Stock_Detail.py", "source_location": "L132"}, {"caller_nid": "3_stock_detail_is_in_watchlist", "callee": "select", "source_file": "streamlit_app\\pages\\3_Stock_Detail.py", "source_location": "L132"}, {"caller_nid": "3_stock_detail_is_in_watchlist", "callee": "table", "source_file": "streamlit_app\\pages\\3_Stock_Detail.py", "source_location": "L132"}, {"caller_nid": "3_stock_detail_is_in_watchlist", "callee": "get_authed_client", "source_file": "streamlit_app\\pages\\3_Stock_Detail.py", "source_location": "L132"}, {"caller_nid": "3_stock_detail_is_in_watchlist", "callee": "len", "source_file": "streamlit_app\\pages\\3_Stock_Detail.py", "source_location": "L141"}, {"caller_nid": "3_stock_detail_toggle_watchlist", "callee": "get_authed_client", "source_file": "streamlit_app\\pages\\3_Stock_Detail.py", "source_location": "L147"}, {"caller_nid": "3_stock_detail_toggle_watchlist", "callee": "execute", "source_file": "streamlit_app\\pages\\3_Stock_Detail.py", "source_location": "L149"}, {"caller_nid": "3_stock_detail_toggle_watchlist", "callee": "upsert", "source_file": "streamlit_app\\pages\\3_Stock_Detail.py", "source_location": "L149"}, {"caller_nid": "3_stock_detail_toggle_watchlist", "callee": "table", "source_file": "streamlit_app\\pages\\3_Stock_Detail.py", "source_location": "L149"}, {"caller_nid": "3_stock_detail_toggle_watchlist", "callee": "execute", "source_file": "streamlit_app\\pages\\3_Stock_Detail.py", "source_location": "L154"}, {"caller_nid": "3_stock_detail_toggle_watchlist", "callee": "eq", "source_file": "streamlit_app\\pages\\3_Stock_Detail.py", "source_location": "L154"}, {"caller_nid": "3_stock_detail_toggle_watchlist", "callee": "eq", "source_file": "streamlit_app\\pages\\3_Stock_Detail.py", "source_location": "L154"}, {"caller_nid": "3_stock_detail_toggle_watchlist", "callee": "delete", "source_file": "streamlit_app\\pages\\3_Stock_Detail.py", "source_location": "L154"}, {"caller_nid": "3_stock_detail_toggle_watchlist", "callee": "table", "source_file": "streamlit_app\\pages\\3_Stock_Detail.py", "source_location": "L154"}]}