{"nodes": [{"id": "data_ingest_compute_indicators_py", "label": "compute_indicators.py", "file_type": "code", "source_file": "data\\ingest\\compute_indicators.py", "source_location": "L1"}, {"id": "compute_indicators_compute_indicators", "label": "compute_indicators()", "file_type": "code", "source_file": "data\\ingest\\compute_indicators.py", "source_location": "L11"}, {"id": "compute_indicators_safe_round", "label": "_safe_round()", "file_type": "code", "source_file": "data\\ingest\\compute_indicators.py", "source_location": "L81"}, {"id": "compute_indicators_rationale_1", "label": "Compute technical indicators for each stock symbol using pandas-ta. Indicators:", "file_type": "rationale", "source_file": "data\\ingest\\compute_indicators.py", "source_location": "L1"}, {"id": "compute_indicators_rationale_12", "label": "Compute technical indicators for each symbol in the OHLCV DataFrame.      Args:", "file_type": "rationale", "source_file": "data\\ingest\\compute_indicators.py", "source_location": "L12"}, {"id": "compute_indicators_rationale_82", "label": "Safely extract and round a value from a pandas Series.", "file_type": "rationale", "source_file": "data\\ingest\\compute_indicators.py", "source_location": "L82"}], "edges": [{"source": "data_ingest_compute_indicators_py", "target": "pandas", "relation": "imports", "confidence": "EXTRACTED", "source_file": "data\\ingest\\compute_indicators.py", "source_location": "L7", "weight": 1.0}, {"source": "data_ingest_compute_indicators_py", "target": "pandas_ta", "relation": "imports", "confidence": "EXTRACTED", "source_file": "data\\ingest\\compute_indicators.py", "source_location": "L8", "weight": 1.0}, {"source": "data_ingest_compute_indicators_py", "target": "compute_indicators_compute_indicators", "relation": "contains", "confidence": "EXTRACTED", "source_file": "data\\ingest\\compute_indicators.py", "source_location": "L11", "weight": 1.0}, {"source": "data_ingest_compute_indicators_py", "target": "compute_indicators_safe_round", "relation": "contains", "confidence": "EXTRACTED", "source_file": "data\\ingest\\compute_indicators.py", "source_location": "L81", "weight": 1.0}, {"source": "data_ingest_compute_indicators_py", "target": "data_ingest_fetch_ohlcv", "relation": "imports_from", "confidence": "EXTRACTED", "source_file": "data\\ingest\\compute_indicators.py", "source_location": "L98", "weight": 1.0}, {"source": "compute_indicators_compute_indicators", "target": "compute_indicators_safe_round", "relation": "calls", "confidence": "EXTRACTED", "source_file": "data\\ingest\\compute_indicators.py", "source_location": "L57", "weight": 1.0}, {"source": "compute_indicators_rationale_1", "target": "data_ingest_compute_indicators_py", "relation": "rationale_for", "confidence": "EXTRACTED", "source_file": "data\\ingest\\compute_indicators.py", "source_location": "L1", "weight": 1.0}, {"source": "compute_indicators_rationale_12", "target": "compute_indicators_compute_indicators", "relation": "rationale_for", "confidence": "EXTRACTED", "source_file": "data\\ingest\\compute_indicators.py", "source_location": "L12", "weight": 1.0}, {"source": "compute_indicators_rationale_82", "target": "compute_indicators_safe_round", "relation": "rationale_for", "confidence": "EXTRACTED", "source_file": "data\\ingest\\compute_indicators.py", "source_location": "L82", "weight": 1.0}], "raw_calls": [{"caller_nid": "compute_indicators_compute_indicators", "callee": "DataFrame", "source_file": "data\\ingest\\compute_indicators.py", "source_location": "L25"}, {"caller_nid": "compute_indicators_compute_indicators", "callee": "unique", "source_file": "data\\ingest\\compute_indicators.py", "source_location": "L29"}, {"caller_nid": "compute_indicators_compute_indicators", "callee": "print", "source_file": "data\\ingest\\compute_indicators.py", "source_location": "L30"}, {"caller_nid": "compute_indicators_compute_indicators", "callee": "len", "source_file": "data\\ingest\\compute_indicators.py", "source_location": "L30"}, {"caller_nid": "compute_indicators_compute_indicators", "callee": "enumerate", "source_file": "data\\ingest\\compute_indicators.py", "source_location": "L32"}, {"caller_nid": "compute_indicators_compute_indicators", "callee": "copy", "source_file": "data\\ingest\\compute_indicators.py", "source_location": "L33"}, {"caller_nid": "compute_indicators_compute_indicators", "callee": "reset_index", "source_file": "data\\ingest\\compute_indicators.py", "source_location": "L34"}, {"caller_nid": "compute_indicators_compute_indicators", "callee": "sort_values", "source_file": "data\\ingest\\compute_indicators.py", "source_location": "L34"}, {"caller_nid": "compute_indicators_compute_indicators", "callee": "len", "source_file": "data\\ingest\\compute_indicators.py", "source_location": "L36"}, {"caller_nid": "compute_indicators_compute_indicators", "callee": "print", "source_file": "data\\ingest\\compute_indicators.py", "source_location": "L37"}, {"caller_nid": "compute_indicators_compute_indicators", "callee": "len", "source_file": "data\\ingest\\compute_indicators.py", "source_location": "L37"}, {"caller_nid": "compute_indicators_compute_indicators", "callee": "to_numeric", "source_file": "data\\ingest\\compute_indicators.py", "source_location": "L41"}, {"caller_nid": "compute_indicators_compute_indicators", "callee": "rsi", "source_file": "data\\ingest\\compute_indicators.py", "source_location": "L43"}, {"caller_nid": "compute_indicators_compute_indicators", "callee": "macd", "source_file": "data\\ingest\\compute_indicators.py", "source_location": "L44"}, {"caller_nid": "compute_indicators_compute_indicators", "callee": "bbands", "source_file": "data\\ingest\\compute_indicators.py", "source_location": "L45"}, {"caller_nid": "compute_indicators_compute_indicators", "callee": "sma", "source_file": "data\\ingest\\compute_indicators.py", "source_location": "L46"}, {"caller_nid": "compute_indicators_compute_indicators", "callee": "sma", "source_file": "data\\ingest\\compute_indicators.py", "source_location": "L47"}, {"caller_nid": "compute_indicators_compute_indicators", "callee": "ema", "source_file": "data\\ingest\\compute_indicators.py", "source_location": "L48"}, {"caller_nid": "compute_indicators_compute_indicators", "callee": "ema", "source_file": "data\\ingest\\compute_indicators.py", "source_location": "L49"}, {"caller_nid": "compute_indicators_compute_indicators", "callee": "atr", "source_file": "data\\ingest\\compute_indicators.py", "source_location": "L50"}, {"caller_nid": "compute_indicators_compute_indicators", "callee": "obv", "source_file": "data\\ingest\\compute_indicators.py", "source_location": "L51"}, {"caller_nid": "compute_indicators_compute_indicators", "callee": "range", "source_file": "data\\ingest\\compute_indicators.py", "source_location": "L53"}, {"caller_nid": "compute_indicators_compute_indicators", "callee": "len", "source_file": "data\\ingest\\compute_indicators.py", "source_location": "L53"}, {"caller_nid": "compute_indicators_compute_indicators", "callee": "append", "source_file": "data\\ingest\\compute_indicators.py", "source_location": "L71"}, {"caller_nid": "compute_indicators_compute_indicators", "callee": "print", "source_file": "data\\ingest\\compute_indicators.py", "source_location": "L74"}, {"caller_nid": "compute_indicators_compute_indicators", "callee": "len", "source_file": "data\\ingest\\compute_indicators.py", "source_location": "L74"}, {"caller_nid": "compute_indicators_compute_indicators", "callee": "DataFrame", "source_file": "data\\ingest\\compute_indicators.py", "source_location": "L76"}, {"caller_nid": "compute_indicators_compute_indicators", "callee": "print", "source_file": "data\\ingest\\compute_indicators.py", "source_location": "L77"}, {"caller_nid": "compute_indicators_compute_indicators", "callee": "len", "source_file": "data\\ingest\\compute_indicators.py", "source_location": "L77"}, {"caller_nid": "compute_indicators_safe_round", "callee": "isna", "source_file": "data\\ingest\\compute_indicators.py", "source_location": "L87"}, {"caller_nid": "compute_indicators_safe_round", "callee": "round", "source_file": "data\\ingest\\compute_indicators.py", "source_location": "L89"}, {"caller_nid": "compute_indicators_safe_round", "callee": "float", "source_file": "data\\ingest\\compute_indicators.py", "source_location": "L89"}, {"caller_nid": "compute_indicators_safe_round", "callee": "int", "source_file": "data\\ingest\\compute_indicators.py", "source_location": "L91"}]}