{"nodes": [{"id": "niveshsutra_services_api_routers_signals_py", "label": "signals.py", "file_type": "code", "source_file": "NiveshSutra\\services\\api\\routers\\signals.py", "source_location": "L1"}, {"id": "signals_list_signals", "label": "list_signals()", "file_type": "code", "source_file": "NiveshSutra\\services\\api\\routers\\signals.py", "source_location": "L9"}, {"id": "signals_signals_summary", "label": "signals_summary()", "file_type": "code", "source_file": "NiveshSutra\\services\\api\\routers\\signals.py", "source_location": "L29"}, {"id": "signals_get_signal_history", "label": "get_signal_history()", "file_type": "code", "source_file": "NiveshSutra\\services\\api\\routers\\signals.py", "source_location": "L42"}, {"id": "signals_get_latest_signal", "label": "get_latest_signal()", "file_type": "code", "source_file": "NiveshSutra\\services\\api\\routers\\signals.py", "source_location": "L59"}], "edges": [{"source": "niveshsutra_services_api_routers_signals_py", "target": "fastapi", "relation": "imports_from", "confidence": "EXTRACTED", "source_file": "NiveshSutra\\services\\api\\routers\\signals.py", "source_location": "L1", "weight": 1.0}, {"source": "niveshsutra_services_api_routers_signals_py", "target": "supabase", "relation": "imports_from", "confidence": "EXTRACTED", "source_file": "NiveshSutra\\services\\api\\routers\\signals.py", "source_location": "L2", "weight": 1.0}, {"source": "niveshsutra_services_api_routers_signals_py", "target": "niveshsutra_services_api_dependencies_py", "relation": "imports_from", "confidence": "EXTRACTED", "source_file": "NiveshSutra\\services\\api\\routers\\signals.py", "source_location": "L3", "weight": 1.0}, {"source": "niveshsutra_services_api_routers_signals_py", "target": "signals_list_signals", "relation": "contains", "confidence": "EXTRACTED", "source_file": "NiveshSutra\\services\\api\\routers\\signals.py", "source_location": "L9", "weight": 1.0}, {"source": "niveshsutra_services_api_routers_signals_py", "target": "signals_signals_summary", "relation": "contains", "confidence": "EXTRACTED", "source_file": "NiveshSutra\\services\\api\\routers\\signals.py", "source_location": "L29", "weight": 1.0}, {"source": "niveshsutra_services_api_routers_signals_py", "target": "signals_get_signal_history", "relation": "contains", "confidence": "EXTRACTED", "source_file": "NiveshSutra\\services\\api\\routers\\signals.py", "source_location": "L42", "weight": 1.0}, {"source": "niveshsutra_services_api_routers_signals_py", "target": "signals_get_latest_signal", "relation": "contains", "confidence": "EXTRACTED", "source_file": "NiveshSutra\\services\\api\\routers\\signals.py", "source_location": "L59", "weight": 1.0}], "raw_calls": [{"caller_nid": "signals_list_signals", "callee": "limit", "source_file": "NiveshSutra\\services\\api\\routers\\signals.py", "source_location": "L13"}, {"caller_nid": "signals_list_signals", "callee": "order", "source_file": "NiveshSutra\\services\\api\\routers\\signals.py", "source_location": "L13"}, {"caller_nid": "signals_list_signals", "callee": "select", "source_file": "NiveshSutra\\services\\api\\routers\\signals.py", "source_location": "L13"}, {"caller_nid": "signals_list_signals", "callee": "table", "source_file": "NiveshSutra\\services\\api\\routers\\signals.py", "source_location": "L13"}, {"caller_nid": "signals_list_signals", "callee": "eq", "source_file": "NiveshSutra\\services\\api\\routers\\signals.py", "source_location": "L15"}, {"caller_nid": "signals_list_signals", "callee": "execute", "source_file": "NiveshSutra\\services\\api\\routers\\signals.py", "source_location": "L16"}, {"caller_nid": "signals_list_signals", "callee": "set", "source_file": "NiveshSutra\\services\\api\\routers\\signals.py", "source_location": "L19"}, {"caller_nid": "signals_list_signals", "callee": "add", "source_file": "NiveshSutra\\services\\api\\routers\\signals.py", "source_location": "L23"}, {"caller_nid": "signals_list_signals", "callee": "append", "source_file": "NiveshSutra\\services\\api\\routers\\signals.py", "source_location": "L24"}, {"caller_nid": "signals_signals_summary", "callee": "execute", "source_file": "NiveshSutra\\services\\api\\routers\\signals.py", "source_location": "L30"}, {"caller_nid": "signals_signals_summary", "callee": "limit", "source_file": "NiveshSutra\\services\\api\\routers\\signals.py", "source_location": "L30"}, {"caller_nid": "signals_signals_summary", "callee": "order", "source_file": "NiveshSutra\\services\\api\\routers\\signals.py", "source_location": "L30"}, {"caller_nid": "signals_signals_summary", "callee": "select", "source_file": "NiveshSutra\\services\\api\\routers\\signals.py", "source_location": "L30"}, {"caller_nid": "signals_signals_summary", "callee": "table", "source_file": "NiveshSutra\\services\\api\\routers\\signals.py", "source_location": "L30"}, {"caller_nid": "signals_signals_summary", "callee": "values", "source_file": "NiveshSutra\\services\\api\\routers\\signals.py", "source_location": "L36"}, {"caller_nid": "signals_signals_summary", "callee": "get", "source_file": "NiveshSutra\\services\\api\\routers\\signals.py", "source_location": "L37"}, {"caller_nid": "signals_signals_summary", "callee": "len", "source_file": "NiveshSutra\\services\\api\\routers\\signals.py", "source_location": "L38"}, {"caller_nid": "signals_get_signal_history", "callee": "execute", "source_file": "NiveshSutra\\services\\api\\routers\\signals.py", "source_location": "L48"}, {"caller_nid": "signals_get_signal_history", "callee": "limit", "source_file": "NiveshSutra\\services\\api\\routers\\signals.py", "source_location": "L48"}, {"caller_nid": "signals_get_signal_history", "callee": "order", "source_file": "NiveshSutra\\services\\api\\routers\\signals.py", "source_location": "L48"}, {"caller_nid": "signals_get_signal_history", "callee": "eq", "source_file": "NiveshSutra\\services\\api\\routers\\signals.py", "source_location": "L48"}, {"caller_nid": "signals_get_signal_history", "callee": "select", "source_file": "NiveshSutra\\services\\api\\routers\\signals.py", "source_location": "L48"}, {"caller_nid": "signals_get_signal_history", "callee": "table", "source_file": "NiveshSutra\\services\\api\\routers\\signals.py", "source_location": "L48"}, {"caller_nid": "signals_get_signal_history", "callee": "sorted", "source_file": "NiveshSutra\\services\\api\\routers\\signals.py", "source_location": "L55"}, {"caller_nid": "signals_get_latest_signal", "callee": "execute", "source_file": "NiveshSutra\\services\\api\\routers\\signals.py", "source_location": "L61"}, {"caller_nid": "signals_get_latest_signal", "callee": "limit", "source_file": "NiveshSutra\\services\\api\\routers\\signals.py", "source_location": "L61"}, {"caller_nid": "signals_get_latest_signal", "callee": "order", "source_file": "NiveshSutra\\services\\api\\routers\\signals.py", "source_location": "L61"}, {"caller_nid": "signals_get_latest_signal", "callee": "eq", "source_file": "NiveshSutra\\services\\api\\routers\\signals.py", "source_location": "L61"}, {"caller_nid": "signals_get_latest_signal", "callee": "select", "source_file": "NiveshSutra\\services\\api\\routers\\signals.py", "source_location": "L61"}, {"caller_nid": "signals_get_latest_signal", "callee": "table", "source_file": "NiveshSutra\\services\\api\\routers\\signals.py", "source_location": "L61"}]}